[{"name":"Alicia"},{"name":"Angadanan"},{"name":"Aurora"},{"name":"Benito Soliven"},{"name":"Burgos"},{"name":"Cabagan"},{"name":"Cabatuan"},{"name":"Cauayan"},{"name":"Cordon"},{"name":"Delfin Albano"},{"name":"Dinapigue"},{"name":"Divilacan"},{"name":"Echague"},{"name":"Gamu"},{"name":"Ilagan"},{"name":"Jones"},{"name":"Luna"},{"name":"Maconacon"},{"name":"Mallig"},{"name":"Naguilian"},{"name":"Quezon"},{"name":"Quirino"},{"name":"Ramon"},{"name":"Reina Mercedes"},{"name":"Roxas"},{"name":"San Agustin"},{"name":"San Guillermo"},{"name":"San Isidro"},{"name":"San Manuel"},{"name":"San Mariano"},{"name":"San Mateo"},{"name":"San Pablo"},{"name":"Santa Maria"},{"name":"Santiago City"},{"name":"Santo Tomas"},{"name":"Tumauini"}]
