[{"name":"Albufeira"},{"name":"Alcantarilha"},{"name":"Alcoutim"},{"name":"Algoz"},{"name":"Aljezur"},{"name":"Almancil"},{"name":"Altura"},{"name":"Alvor"},{"name":"Armação de Pêra"},{"name":"Bensafrim"},{"name":"Boliqueime"},{"name":"Cabanas de Tavira"},{"name":"Carvoeiro"},{"name":"Castro Marim"},{"name":"Conceição"},{"name":"Estói"},{"name":"Estômbar"},{"name":"Faro"},{"name":"Ferragudo"},{"name":"Ferreiras"},{"name":"Fuzeta"},{"name":"Guia"},{"name":"Lagoa"},{"name":"Lagos"},{"name":"Laranjeiro"},{"name":"Loulé"},{"name":"Luz"},{"name":"Manta Rota"},{"name":"Marmelete"},{"name":"Mexilhoeira Grande"},{"name":"Moncarapacho"},{"name":"Monchique"},{"name":"Monte Gordo"},{"name":"Olhão"},{"name":"Olhos de Água"},{"name":"Paderne"},{"name":"Parchal"},{"name":"Pêra"},{"name":"Porches"},{"name":"Portimão"},{"name":"Quarteira"},{"name":"Sagres"},{"name":"Santa Bárbara de Nexe"},{"name":"Santa Luzia"},{"name":"São Bartolomeu de Messines"},{"name":"São Brás de Alportel"},{"name":"São Marcos da Serra"},{"name":"Senhora da Luz"},{"name":"Silves"},{"name":"Tavira"},{"name":"Tunes"},{"name":"Vila do Bispo"},{"name":"Vila Nova De Cacela"},{"name":"Vila Real de Santo António"},{"name":"Vilamoura"}]
