[{"name":"Aghireșu"},{"name":"Aghireșu-Fabrici"},{"name":"Aiton"},{"name":"Aluniş"},{"name":"Apahida"},{"name":"Aşchileu Dorna"},{"name":"Baciu"},{"name":"Băişoara"},{"name":"Beliş"},{"name":"Bobâlna"},{"name":"Bogdăneşti"},{"name":"Bonțida"},{"name":"Borşa"},{"name":"Buza"},{"name":"Căianu"},{"name":"Căianu Mic"},{"name":"Călăraşi"},{"name":"Călăţele"},{"name":"Cămăraşu"},{"name":"Câmpia Turzii"},{"name":"Căpuşu Mare"},{"name":"Căşeiu"},{"name":"Câţcău"},{"name":"Cătina"},{"name":"Ceanu Mare"},{"name":"Chinteni"},{"name":"Chiuiești"},{"name":"Ciucea"},{"name":"Ciurila"},{"name":"Cluj-Napoca"},{"name":"Cojocna"},{"name":"Comuna Aghireşu"},{"name":"Comuna Aiton"},{"name":"Comuna Aluniş"},{"name":"Comuna Apahida"},{"name":"Comuna Aşchileu"},{"name":"Comuna Baciu"},{"name":"Comuna Băişoara"},{"name":"Comuna Beliş"},{"name":"Comuna Bobâlna"},{"name":"Comuna Bonţida"},{"name":"Comuna Borşa"},{"name":"Comuna Buza"},{"name":"Comuna Căianu"},{"name":"Comuna Călăraşi"},{"name":"Comuna Călăţele"},{"name":"Comuna Cămăraşu"},{"name":"Comuna Cãpuşu Mare"},{"name":"Comuna Căşeiu"},{"name":"Comuna Câţcău"},{"name":"Comuna Cătina"},{"name":"Comuna Ceanu Mare"},{"name":"Comuna Chinteni"},{"name":"Comuna Chiuieşti"},{"name":"Comuna Ciucea"},{"name":"Comuna Ciurila"},{"name":"Comuna Cojocna"},{"name":"Comuna Corneşti"},{"name":"Comuna Cuzdrioara"},{"name":"Comuna Dăbâca"},{"name":"Comuna Feleacu"},{"name":"Comuna Fizeşu Gherlii"},{"name":"Comuna Floreşti"},{"name":"Comuna Frata"},{"name":"Comuna Gârbãu"},{"name":"Comuna Geaca"},{"name":"Comuna Gilău"},{"name":"Comuna Iara"},{"name":"Comuna Iclod"},{"name":"Comuna Izvoru Crişului"},{"name":"Comuna Jichişu De Jos"},{"name":"Comuna Jucu"},{"name":"Comuna Luna"},{"name":"Comuna Mãguri-Rãcãtãu"},{"name":"Comuna Mânăstireni"},{"name":"Comuna Mărgău"},{"name":"Comuna Mărişel"},{"name":"Comuna Mica"},{"name":"Comuna Mihai Viteazu"},{"name":"Comuna Mintiu Gherlii"},{"name":"Comuna Mociu"},{"name":"Comuna Moldoveneşti"},{"name":"Comuna Negreni"},{"name":"Comuna Pãlatca"},{"name":"Comuna Panticeu"},{"name":"Comuna Petreştii De Jos"},{"name":"Comuna Ploscoş"},{"name":"Comuna Poieni"},{"name":"Comuna Râșca"},{"name":"Comuna Recea Cristur"},{"name":"Comuna Sãcuieu"},{"name":"Comuna Sâncraiu"},{"name":"Comuna Sănduleşti"},{"name":"Comuna Sânmărtin"},{"name":"Comuna Sânpaul"},{"name":"Comuna Săvădisla"},{"name":"Comuna Sic"},{"name":"Comuna Suatu"},{"name":"Comuna Ţaga"},{"name":"Comuna Tritenii De Jos"},{"name":"Comuna Tureni"},{"name":"Comuna Vad"},{"name":"Comuna Valea Ierii"},{"name":"Comuna Viişoara"},{"name":"Comuna Vultureni"},{"name":"Copăceni"},{"name":"Corneşti"},{"name":"Cuzdrioara"},{"name":"Dăbâca"},{"name":"Dej"},{"name":"Dezmir"},{"name":"Feleacu"},{"name":"Fizeşu Gherlii"},{"name":"Floreşti"},{"name":"Frata"},{"name":"Gârbău"},{"name":"Geaca"},{"name":"Gheorghieni"},{"name":"Gherla"},{"name":"Gilău"},{"name":"Huedin"},{"name":"Iara"},{"name":"Iclod"},{"name":"Izvoru Crişului"},{"name":"Jichişu de Jos"},{"name":"Luna"},{"name":"Luna de Sus"},{"name":"Luncani"},{"name":"Măguri"},{"name":"Măguri-Răcătău"},{"name":"Mânăstireni"},{"name":"Mărgău"},{"name":"Mărişel"},{"name":"Mera"},{"name":"Mica"},{"name":"Mihai Viteazu"},{"name":"Mintiu Gherlii"},{"name":"Mociu"},{"name":"Moldoveneşti"},{"name":"Municipiul Câmpia Turzii"},{"name":"Municipiul Cluj-Napoca"},{"name":"Municipiul Dej"},{"name":"Municipiul Gherla"},{"name":"Municipiul Turda"},{"name":"Negreni"},{"name":"Nireș"},{"name":"Ocna Dejului"},{"name":"Oraş Huedin"},{"name":"Pădureni"},{"name":"Pălatca"},{"name":"Panticeu"},{"name":"Petreştii de Jos"},{"name":"Ploscoș"},{"name":"Poieni"},{"name":"Râșca"},{"name":"Răscruci"},{"name":"Recea Cristur"},{"name":"Rugășești"},{"name":"Săcuieu"},{"name":"Sâncraiu"},{"name":"Sănduleşti"},{"name":"Sânmărghita"},{"name":"Sânmărtin"},{"name":"Sânnicoară"},{"name":"Sânpaul"},{"name":"Săvădisla"},{"name":"Sic"},{"name":"Soporu de Câmpie"},{"name":"Suatu"},{"name":"Suceagu"},{"name":"Ţaga"},{"name":"Tritenii de Jos"},{"name":"Tritenii de Sus"},{"name":"Turda"},{"name":"Tureni"},{"name":"Unguraş"},{"name":"Urca"},{"name":"Vad"},{"name":"Vaida-Cămăraș"},{"name":"Valea Ierii"},{"name":"Viişoara"},{"name":"Vultureni"}]
