[{"name":"Bâcleș"},{"name":"Baia de Aramă"},{"name":"Bala"},{"name":"Bălăciţa"},{"name":"Balta"},{"name":"Balta Verde"},{"name":"Bâlvăneşti"},{"name":"Bistrița"},{"name":"Braniștea"},{"name":"Brezniţa Ocol"},{"name":"Brezniţa-Motru"},{"name":"Broşteni"},{"name":"Burila Mare"},{"name":"Butoieşti"},{"name":"Căzăneşti"},{"name":"Cerneți"},{"name":"Ciochiuța"},{"name":"Cioroboreni"},{"name":"Cireşu"},{"name":"Comanda"},{"name":"Comuna Bâcleş"},{"name":"Comuna Bala"},{"name":"Comuna Bălăciţa"},{"name":"Comuna Balta"},{"name":"Comuna Bâlvăneşti"},{"name":"Comuna Braniştea"},{"name":"Comuna Brezniţa Ocol"},{"name":"Comuna Brezniţa-Motru"},{"name":"Comuna Broşteni"},{"name":"Comuna Burila Mare"},{"name":"Comuna Butoieşti"},{"name":"Comuna Căzăneşti"},{"name":"Comuna Cireşu"},{"name":"Comuna Corcova"},{"name":"Comuna Corlăţel"},{"name":"Comuna Cujmir"},{"name":"Comuna Dârvari"},{"name":"Comuna Devesel"},{"name":"Comuna Dubova"},{"name":"Comuna Dumbrava"},{"name":"Comuna Eşelniţa"},{"name":"Comuna Floreşti"},{"name":"Comuna Gârla Mare"},{"name":"Comuna Godeanu"},{"name":"Comuna Gogoşu"},{"name":"Comuna Greci"},{"name":"Comuna Grozeşti"},{"name":"Comuna Gruia"},{"name":"Comuna Hinova"},{"name":"Comuna Husnicioara"},{"name":"Comuna Ilovăt"},{"name":"Comuna Iloviţa"},{"name":"Comuna Isverna"},{"name":"Comuna Izvoru Bârzii"},{"name":"Comuna Jiana"},{"name":"Comuna Livezile"},{"name":"Comuna Malovãţ"},{"name":"Comuna Obârşia De Câmp"},{"name":"Comuna Oprişor"},{"name":"Comuna Padina"},{"name":"Comuna Pătulele"},{"name":"Comuna Podeni"},{"name":"Comuna Ponoarele"},{"name":"Comuna Poroina Mare"},{"name":"Comuna Pristol"},{"name":"Comuna Prunişor"},{"name":"Comuna Punghina"},{"name":"Comuna Rogova"},{"name":"Comuna Salcia"},{"name":"Comuna Simian"},{"name":"Comuna Siseşti"},{"name":"Comuna Sovarna"},{"name":"Comuna Stângăceaua"},{"name":"Comuna Sviniţa"},{"name":"Comuna Tâmna"},{"name":"Comuna Vânători"},{"name":"Comuna Vânjuleţ"},{"name":"Comuna Vlădaia"},{"name":"Comuna Voloiac"},{"name":"Corcova"},{"name":"Corlăţel"},{"name":"Cujmir"},{"name":"Dănceu"},{"name":"Dârvari"},{"name":"Devesel"},{"name":"Drobeta-Turnu Severin"},{"name":"Dubova"},{"name":"Dudașu"},{"name":"Dumbrava de Sus"},{"name":"Eşelniţa"},{"name":"Floreşti"},{"name":"Gârla-Mare"},{"name":"Gemeni"},{"name":"Godeanu"},{"name":"Gogoşu"},{"name":"Greci"},{"name":"Grozeşti"},{"name":"Gruia"},{"name":"Gura Văii"},{"name":"Gvardinița"},{"name":"Halânga"},{"name":"Hinova"},{"name":"Husnicioara"},{"name":"Ilovăț"},{"name":"Iloviţa"},{"name":"Isverna"},{"name":"Izimșa"},{"name":"Izvoarele"},{"name":"Izvoru Bârzii"},{"name":"Jiana"},{"name":"Jiana Veche"},{"name":"Jidoștița"},{"name":"Jirov"},{"name":"Livezile"},{"name":"Malovăţ"},{"name":"Municipiul Drobeta-Turnu Severin"},{"name":"Municipiul Orşova"},{"name":"Nicolae Bălcescu"},{"name":"Obârșia de Câmp"},{"name":"Obârşia-Cloşani"},{"name":"Oprişor"},{"name":"Oraş Baia De Aramã"},{"name":"Oraş Strehaia"},{"name":"Oraş Vânju Mare"},{"name":"Orevița Mare"},{"name":"Orşova"},{"name":"Ostrovu Mare"},{"name":"Padina Mică"},{"name":"Pătulele"},{"name":"Podeni"},{"name":"Ponoarele"},{"name":"Poroina Mare"},{"name":"Pristol"},{"name":"Prunişor"},{"name":"Punghina"},{"name":"Recea"},{"name":"Rogova"},{"name":"Roșiori"},{"name":"Salcia"},{"name":"Şimian"},{"name":"Şişeşti"},{"name":"Şovarna"},{"name":"Stângăceaua"},{"name":"Strehaia"},{"name":"Sviniţa"},{"name":"Tâmna"},{"name":"Vânători"},{"name":"Vânju-Mare"},{"name":"Vânjuleţ"},{"name":"Vlădaia"},{"name":"Voloiac"},{"name":"Vrata"}]
