[{"name":"Amirdzhan"},{"name":"Badamdar"},{"name":"Bakıxanov"},{"name":"Baku"},{"name":"Balakhani"},{"name":"Bilajari"},{"name":"Bilajer"},{"name":"Binagadi"},{"name":"Biny Selo"},{"name":"Buzovna"},{"name":"Hövsan"},{"name":"Khodzhi-Gasan"},{"name":"Korgöz"},{"name":"Lökbatan"},{"name":"Mardakan"},{"name":"Maştağa"},{"name":"Nardaran"},{"name":"Nizami Rayonu"},{"name":"Pirallahı"},{"name":"Puta"},{"name":"Qala"},{"name":"Qaraçuxur"},{"name":"Qobustan"},{"name":"Ramana"},{"name":"Sabunçu"},{"name":"Sanqaçal"},{"name":"Türkan"},{"name":"Yeni Suraxanı"},{"name":"Zabrat"},{"name":"Zyrya"}]
