[{"name":"Aktash"},{"name":"Artybash"},{"name":"Belyashi"},{"name":"Chemal"},{"name":"Cherga"},{"name":"Choya"},{"name":"Elekmonar"},{"name":"Gorno-Altaysk"},{"name":"Inya"},{"name":"Iogach"},{"name":"Kosh-Agach"},{"name":"Manzherok"},{"name":"Mayma"},{"name":"Mayminskiy Rayon"},{"name":"Onguday"},{"name":"Ongudayskiy Rayon"},{"name":"Shebalino"},{"name":"Shebalinskiy Rayon"},{"name":"Souzga"},{"name":"Tashanta"},{"name":"Turochak"},{"name":"Ust’-Kan"},{"name":"Ust’-Koksa"},{"name":"Ust’-Koksinskiy Rayon"},{"name":"Ust’-Ulagan"}]
