[{"name":"Abádszalók"},{"name":"Alattyán"},{"name":"Besenyszög"},{"name":"Cibakháza"},{"name":"Cserkeszőlő"},{"name":"Fegyvernek"},{"name":"Jánoshida"},{"name":"Jászalsószentgyörgy"},{"name":"Jászapáti"},{"name":"Jászapáti Járás"},{"name":"Jászárokszállás"},{"name":"Jászberény"},{"name":"Jászberényi Járás"},{"name":"Jászdózsa"},{"name":"Jászjákóhalma"},{"name":"Jászkisér"},{"name":"Jászladány"},{"name":"Jászszentandrás"},{"name":"Karcag"},{"name":"Karcagi Járás"},{"name":"Kenderes"},{"name":"Kengyel"},{"name":"Kisújszállás"},{"name":"Kunhegyes"},{"name":"Kunhegyesi Járás"},{"name":"Kunmadaras"},{"name":"Kunszentmárton"},{"name":"Kunszentmártoni Járás"},{"name":"Mezőtúr"},{"name":"Mezőtúri Járás"},{"name":"Öcsöd"},{"name":"Rákóczifalva"},{"name":"Rákócziújfalu"},{"name":"Szajol"},{"name":"Szelevény"},{"name":"Szolnok"},{"name":"Szolnoki Járás"},{"name":"Tiszabő"},{"name":"Tiszabura"},{"name":"Tiszaföldvár"},{"name":"Tiszafüred"},{"name":"Tiszafüredi Járás"},{"name":"Tiszapüspöki"},{"name":"Tiszaroff"},{"name":"Tiszasüly"},{"name":"Tiszaszentimre"},{"name":"Tiszaszőlős"},{"name":"Törökszentmiklós"},{"name":"Törökszentmiklósi Járás"},{"name":"Tószeg"},{"name":"Túrkeve"},{"name":"Újszász"},{"name":"Zagyvarékas"}]
