[{"name":"Amherst"},{"name":"Annapolis"},{"name":"Antigonish"},{"name":"Berwick"},{"name":"Bridgewater"},{"name":"Cape Breton"},{"name":"Chester"},{"name":"Colchester"},{"name":"Cole Harbour"},{"name":"Cow Bay"},{"name":"Dartmouth"},{"name":"Digby"},{"name":"Digby County"},{"name":"English Corner"},{"name":"Eskasoni 3"},{"name":"Fall River"},{"name":"Glace Bay"},{"name":"Greenwood"},{"name":"Halifax"},{"name":"Hantsport"},{"name":"Hayes Subdivision"},{"name":"Kentville"},{"name":"Lake Echo"},{"name":"Lantz"},{"name":"Lower Sackville"},{"name":"Lunenburg"},{"name":"Middleton"},{"name":"New Glasgow"},{"name":"Oxford"},{"name":"Parrsboro"},{"name":"Pictou"},{"name":"Pictou County"},{"name":"Port Hawkesbury"},{"name":"Port Williams"},{"name":"Princeville"},{"name":"Shelburne"},{"name":"Springhill"},{"name":"Sydney"},{"name":"Sydney Mines"},{"name":"Truro"},{"name":"Windsor"},{"name":"Wolfville"},{"name":"Yarmouth"}]
