[{"name":"An Cabhán"},{"name":"Bailieborough"},{"name":"Ballybofey"},{"name":"Ballyconnell"},{"name":"Ballyjamesduff"},{"name":"Ballyshannon"},{"name":"Belturbet"},{"name":"Buncrana"},{"name":"Bundoran"},{"name":"Carndonagh"},{"name":"Carrickmacross"},{"name":"Castleblayney"},{"name":"Cavan"},{"name":"Clones"},{"name":"Convoy"},{"name":"Cootehill"},{"name":"County Donegal"},{"name":"County Monaghan"},{"name":"Derrybeg"},{"name":"Donegal"},{"name":"Dungloe"},{"name":"Dunlewy"},{"name":"Gweedore"},{"name":"Killybegs"},{"name":"Kingscourt"},{"name":"Leifear"},{"name":"Letterkenny"},{"name":"Monaghan"},{"name":"Moville"},{"name":"Muff"},{"name":"Mullagh"},{"name":"Newtown Cunningham"},{"name":"Ramelton"},{"name":"Raphoe"},{"name":"Virginia"}]
