[{"name":"Aberdeen"},{"name":"Adams County"},{"name":"Ahtanum"},{"name":"Airway Heights"},{"name":"Alderton"},{"name":"Alderwood Manor"},{"name":"Algona"},{"name":"Allyn"},{"name":"Amboy"},{"name":"Ames Lake"},{"name":"Anacortes"},{"name":"Arlington"},{"name":"Arlington Heights"},{"name":"Artondale"},{"name":"Asotin"},{"name":"Asotin County"},{"name":"Auburn"},{"name":"Ault Field"},{"name":"Bainbridge Island"},{"name":"Bangor Trident Base"},{"name":"Barberton"},{"name":"Basin City"},{"name":"Battle Ground"},{"name":"Belfair"},{"name":"Bellevue"},{"name":"Bellingham"},{"name":"Benton City"},{"name":"Benton County"},{"name":"Bethel"},{"name":"Big Lake"},{"name":"Birch Bay"},{"name":"Black Diamond"},{"name":"Blaine"},{"name":"Bonney Lake"},{"name":"Bothell"},{"name":"Bothell East"},{"name":"Bothell West"},{"name":"Boulevard Park"},{"name":"Bremerton"},{"name":"Brewster"},{"name":"Bridgeport"},{"name":"Brier"},{"name":"Browns Point"},{"name":"Brush Prairie"},{"name":"Bryant"},{"name":"Bryn Mawr-Skyway"},{"name":"Buckley"},{"name":"Bunk Foss"},{"name":"Burbank"},{"name":"Burien"},{"name":"Burley"},{"name":"Burlington"},{"name":"Camano"},{"name":"Camas"},{"name":"Canterwood"},{"name":"Carnation"},{"name":"Carson"},{"name":"Cascade Valley"},{"name":"Cashmere"},{"name":"Castle Rock"},{"name":"Cathcart"},{"name":"Cathlamet"},{"name":"Central Park"},{"name":"Centralia"},{"name":"Chehalis"},{"name":"Chelan"},{"name":"Chelan County"},{"name":"Cheney"},{"name":"Chewelah"},{"name":"Chico"},{"name":"City of Sammamish"},{"name":"Clallam"},{"name":"Clark County"},{"name":"Clarkston"},{"name":"Clarkston Heights-Vineland"},{"name":"Cle Elum"},{"name":"Clear Lake"},{"name":"Clearview"},{"name":"Clyde Hill"},{"name":"Colfax"},{"name":"College Place"},{"name":"Columbia County"},{"name":"Colville"},{"name":"Connell"},{"name":"Cosmopolis"},{"name":"Cottage Lake"},{"name":"Coulee Dam"},{"name":"Country Homes"},{"name":"Coupeville"},{"name":"Covington"},{"name":"Cowlitz"},{"name":"Crocker"},{"name":"Dallesport"},{"name":"Darrington"},{"name":"Davenport"},{"name":"Dayton"},{"name":"Deer Park"},{"name":"Des Moines"},{"name":"Desert Aire"},{"name":"Dishman"},{"name":"Dollar Corner"},{"name":"Douglas County"},{"name":"DuPont"},{"name":"Duvall"},{"name":"East Hill-Meridian"},{"name":"East Port Orchard"},{"name":"East Renton Highlands"},{"name":"East Wenatchee"},{"name":"East Wenatchee Bench"},{"name":"Eastgate"},{"name":"Eastmont"},{"name":"Eatonville"},{"name":"Edgewood"},{"name":"Edmonds"},{"name":"Electric City"},{"name":"Elk Plain"},{"name":"Ellensburg"},{"name":"Elma"},{"name":"Enetai"},{"name":"Entiat"},{"name":"Enumclaw"},{"name":"Ephrata"},{"name":"Erlands Point-Kitsap Lake"},{"name":"Esperance"},{"name":"Everett"},{"name":"Everson"},{"name":"Fairchild Air Force Base"},{"name":"Fairwood"},{"name":"Fall City"},{"name":"Federal Way"},{"name":"Felida"},{"name":"Fern Prairie"},{"name":"Ferndale"},{"name":"Ferry"},{"name":"Fife"},{"name":"Fife Heights"},{"name":"Finley"},{"name":"Fircrest"},{"name":"Five Corners"},{"name":"Fobes Hill"},{"name":"Fords Prairie"},{"name":"Forks"},{"name":"Fox Island"},{"name":"Franklin County"},{"name":"Frederickson"},{"name":"Freeland"},{"name":"Friday Harbor"},{"name":"Garfield"},{"name":"Garrett"},{"name":"Geneva"},{"name":"Gig Harbor"},{"name":"Gleed"},{"name":"Gold Bar"},{"name":"Goldendale"},{"name":"Graham"},{"name":"Grand Coulee"},{"name":"Grand Mound"},{"name":"Grandview"},{"name":"Granger"},{"name":"Granite Falls"},{"name":"Grant County"},{"name":"Grays Harbor"},{"name":"Hansville"},{"name":"Hazel Dell"},{"name":"Highland"},{"name":"Hobart"},{"name":"Hockinson"},{"name":"Home"},{"name":"Hoquiam"},{"name":"Indianola"},{"name":"Inglewood-Finn Hill"},{"name":"Island"},{"name":"Issaquah"},{"name":"Jefferson County"},{"name":"Joint Base Lewis McChord"},{"name":"Kalama"},{"name":"Kelso"},{"name":"Kenmore"},{"name":"Kennewick"},{"name":"Kent"},{"name":"Kettle Falls"},{"name":"Key Center"},{"name":"King"},{"name":"Kingsgate"},{"name":"Kingston"},{"name":"Kirkland"},{"name":"Kitsap"},{"name":"Kittitas"},{"name":"Kittitas County"},{"name":"Klahanie"},{"name":"Klickitat"},{"name":"La Center"},{"name":"Lacey"},{"name":"Lake Forest Park"},{"name":"Lake Marcel-Stillwater"},{"name":"Lake Morton-Berrydale"},{"name":"Lake Shore"},{"name":"Lake Stevens"},{"name":"Lake Stickney"},{"name":"Lakeland North"},{"name":"Lakeland South"},{"name":"Lakewood"},{"name":"Langley"},{"name":"Larch Way"},{"name":"Lea Hill"},{"name":"Leavenworth"},{"name":"Lewis"},{"name":"Lewisville"},{"name":"Liberty Lake"},{"name":"Lincoln County"},{"name":"Lochsloy"},{"name":"Lofall"},{"name":"Long Beach"},{"name":"Longbranch"},{"name":"Longview"},{"name":"Longview Heights"},{"name":"Lynden"},{"name":"Lynnwood"},{"name":"Mabton"},{"name":"Machias"},{"name":"Maltby"},{"name":"Manchester"},{"name":"Manson"},{"name":"Maple Heights-Lake Desire"},{"name":"Maple Valley"},{"name":"Maplewood"},{"name":"Marietta"},{"name":"Marietta-Alderwood"},{"name":"Martha Lake"},{"name":"Marysville"},{"name":"Mason County"},{"name":"Mattawa"},{"name":"McChord Air Force Base"},{"name":"McCleary"},{"name":"McMillin"},{"name":"Mead"},{"name":"Meadow Glade"},{"name":"Meadowdale"},{"name":"Medical Lake"},{"name":"Medina"},{"name":"Mercer Island"},{"name":"Midland"},{"name":"Mill Creek"},{"name":"Mill Creek East"},{"name":"Mill Plain"},{"name":"Millwood"},{"name":"Milton"},{"name":"Minnehaha"},{"name":"Mirrormont"},{"name":"Monroe"},{"name":"Monroe North"},{"name":"Montesano"},{"name":"Morton"},{"name":"Moses Lake"},{"name":"Moses Lake North"},{"name":"Mount Vernon"},{"name":"Mount Vista"},{"name":"Mountlake Terrace"},{"name":"Mukilteo"},{"name":"Napavine"},{"name":"Navy Yard City"},{"name":"Newcastle"},{"name":"Newport"},{"name":"Nooksack"},{"name":"Normandy Park"},{"name":"North Bend"},{"name":"North Creek"},{"name":"North Fort Lewis"},{"name":"North Puyallup"},{"name":"North Yelm"},{"name":"Oak Harbor"},{"name":"Ocean Park"},{"name":"Ocean Shores"},{"name":"Okanogan"},{"name":"Okanogan County"},{"name":"Olympia"},{"name":"Omak"},{"name":"Opportunity"},{"name":"Orchards"},{"name":"Oroville"},{"name":"Orting"},{"name":"Othello"},{"name":"Otis Orchards-East Farms"},{"name":"Pacific"},{"name":"Pacific County"},{"name":"Palouse"},{"name":"Parkland"},{"name":"Parkwood"},{"name":"Pasco"},{"name":"Peaceful Valley"},{"name":"Pend Oreille"},{"name":"Picnic Point"},{"name":"Picnic Point-North Lynnwood"},{"name":"Pierce County"},{"name":"Point Roberts"},{"name":"Pomeroy"},{"name":"Port Angeles"},{"name":"Port Angeles East"},{"name":"Port Hadlock-Irondale"},{"name":"Port Ludlow"},{"name":"Port Orchard"},{"name":"Port Townsend"},{"name":"Poulsbo"},{"name":"Prairie Heights"},{"name":"Prairie Ridge"},{"name":"Prosser"},{"name":"Pullman"},{"name":"Purdy"},{"name":"Puyallup"},{"name":"Quincy"},{"name":"Rainier"},{"name":"Ravensdale"},{"name":"Raymond"},{"name":"Redmond"},{"name":"Renton"},{"name":"Republic"},{"name":"Richland"},{"name":"Ridgefield"},{"name":"Ritzville"},{"name":"Riverbend"},{"name":"Riverton"},{"name":"Rochester"},{"name":"Rocky Point"},{"name":"Rosedale"},{"name":"Royal City"},{"name":"Salmon Creek"},{"name":"Sammamish"},{"name":"San Juan"},{"name":"Seabeck"},{"name":"SeaTac"},{"name":"Seattle"},{"name":"Sedro-Woolley"},{"name":"Selah"},{"name":"Sequim"},{"name":"Shelton"},{"name":"Shoreline"},{"name":"Silver Firs"},{"name":"Silverdale"},{"name":"Sisco Heights"},{"name":"Skagit"},{"name":"Skamania"},{"name":"Smokey Point"},{"name":"Snohomish"},{"name":"Snohomish County"},{"name":"Snoqualmie"},{"name":"Soap Lake"},{"name":"South Bend"},{"name":"South Hill"},{"name":"South Wenatchee"},{"name":"Southworth"},{"name":"Spanaway"},{"name":"Spokane"},{"name":"Spokane County"},{"name":"Spokane Valley"},{"name":"Stanwood"},{"name":"Steilacoom"},{"name":"Stevens"},{"name":"Stevenson"},{"name":"Sudden Valley"},{"name":"Sultan"},{"name":"Sumas"},{"name":"Summit"},{"name":"Summit View"},{"name":"Sumner"},{"name":"Sunnyside"},{"name":"Sunnyslope"},{"name":"Suquamish"},{"name":"Tacoma"},{"name":"Tanglewilde"},{"name":"Tanglewilde-Thompson Place"},{"name":"Tanner"},{"name":"Tenino"},{"name":"Terrace Heights"},{"name":"Three Lakes"},{"name":"Thurston"},{"name":"Tieton"},{"name":"Tonasket"},{"name":"Toppenish"},{"name":"Town and Country"},{"name":"Tracyton"},{"name":"Trentwood"},{"name":"Tukwila"},{"name":"Tulalip"},{"name":"Tulalip Bay"},{"name":"Tumwater"},{"name":"Union Gap"},{"name":"Union Hill-Novelty Hill"},{"name":"University Place"},{"name":"Vancouver"},{"name":"Vashon"},{"name":"Venersborg"},{"name":"Veradale"},{"name":"Wahkiakum"},{"name":"Waitsburg"},{"name":"Walla Walla"},{"name":"Walla Walla County"},{"name":"Walla Walla East"},{"name":"Waller"},{"name":"Walnut Grove"},{"name":"Wapato"},{"name":"Warden"},{"name":"Warm Beach"},{"name":"Washougal"},{"name":"Waterville"},{"name":"Wauna"},{"name":"Wenatchee"},{"name":"West Clarkston-Highland"},{"name":"West Lake Sammamish"},{"name":"West Lake Stevens"},{"name":"West Longview"},{"name":"West Pasco"},{"name":"West Richland"},{"name":"West Side Highway"},{"name":"West Valley"},{"name":"West Wenatchee"},{"name":"Westport"},{"name":"Whatcom"},{"name":"White Center"},{"name":"White Salmon"},{"name":"Whitman"},{"name":"Wilderness Rim"},{"name":"Winlock"},{"name":"Wollochet"},{"name":"Woodinville"},{"name":"Woodland"},{"name":"Woods Creek"},{"name":"Woodway"},{"name":"Yacolt"},{"name":"Yakima"},{"name":"Yakima County"},{"name":"Yarrow Point"},{"name":"Yelm"},{"name":"Zillah"}]
