[{"name":"Akalla"},{"name":"Åkersberga"},{"name":"Alby"},{"name":"Älmsta"},{"name":"Älta"},{"name":"Arnö"},{"name":"Årsta"},{"name":"Bergshamra"},{"name":"Bollmora"},{"name":"Boo"},{"name":"Brevik"},{"name":"Bro"},{"name":"Bromma"},{"name":"Brunn"},{"name":"Brunna"},{"name":"Dalarö"},{"name":"Djurö"},{"name":"Djursholm"},{"name":"Ekerö"},{"name":"Enebyberg"},{"name":"Eriksberg"},{"name":"Fisksätra"},{"name":"Fittja"},{"name":"Gamla Stan"},{"name":"Gustavsberg"},{"name":"Hallstavik"},{"name":"Handen"},{"name":"Haninge"},{"name":"Hemmesta"},{"name":"Hölö"},{"name":"Huddinge"},{"name":"Jakobsberg"},{"name":"Järna"},{"name":"Jordbro"},{"name":"Kista"},{"name":"Kopparmora"},{"name":"Kummelnäs"},{"name":"Kungsängen"},{"name":"Kungsholmen"},{"name":"Långvik"},{"name":"Lidingö"},{"name":"Lindholmen"},{"name":"Märsta"},{"name":"Mölnbo"},{"name":"Mörtnäs"},{"name":"Nacka"},{"name":"Norrtälje"},{"name":"Nykvarn"},{"name":"Nynäshamn"},{"name":"Ösmo"},{"name":"Östermalm"},{"name":"Pershagen"},{"name":"Råsunda"},{"name":"Resarö"},{"name":"Rimbo"},{"name":"Rindö"},{"name":"Rönninge"},{"name":"Rosersberg"},{"name":"Saltsjöbaden"},{"name":"Segeltorp"},{"name":"Sigtuna"},{"name":"Skänninge"},{"name":"Södermalm"},{"name":"Södertälje"},{"name":"Sollentuna"},{"name":"Solna"},{"name":"Stavsnäs"},{"name":"Stenhamra"},{"name":"Stockholm"},{"name":"Strömma"},{"name":"Sundbyberg"},{"name":"Tensta"},{"name":"Tullinge"},{"name":"Tumba"},{"name":"Upplands Väsby"},{"name":"Vallentuna"},{"name":"Vårby"},{"name":"Vårsta"},{"name":"Vasastan"},{"name":"Vaxholm"}]
