[{"name":"Ambleside"},{"name":"Appleby-in-Westmorland"},{"name":"Aspatria"},{"name":"Burneside"},{"name":"Carlisle"},{"name":"Cleator Moor"},{"name":"Cockermouth"},{"name":"Cumbria"},{"name":"Dalston"},{"name":"Dearham"},{"name":"Denton Holme"},{"name":"Distington"},{"name":"Egremont"},{"name":"Flimby"},{"name":"Frizington"},{"name":"Kendal"},{"name":"Keswick"},{"name":"Kirkby Stephen"},{"name":"Maryport"},{"name":"Penrith"},{"name":"Saint Bees"},{"name":"Scotby"},{"name":"Seascale"},{"name":"Sedbergh"},{"name":"Shap"},{"name":"Silloth"},{"name":"Wetheral"},{"name":"Whitehaven"},{"name":"Wigton"},{"name":"Windermere"},{"name":"Workington"}]
