[{"name":"Arnside"},{"name":"Barnoldswick"},{"name":"Bay Horse"},{"name":"Billington"},{"name":"Bolton le Sands"},{"name":"Carnforth"},{"name":"Caton"},{"name":"Catterall"},{"name":"Chatburn"},{"name":"Clitheroe"},{"name":"Galgate"},{"name":"Garstang"},{"name":"Goosnargh"},{"name":"Hellifield"},{"name":"High Bentham"},{"name":"Ingleton"},{"name":"Kirkby Lonsdale"},{"name":"Lancashire"},{"name":"Lancaster"},{"name":"Langho"},{"name":"Longridge"},{"name":"Milnthorpe"},{"name":"Morecambe"},{"name":"Preston"},{"name":"Sabden"},{"name":"Settle"},{"name":"Silverdale"},{"name":"Warton"},{"name":"Whalley"}]
