[{"name":"Blaby"},{"name":"Broughton Astley"},{"name":"City of Leicester"},{"name":"Cosby"},{"name":"Countesthorpe"},{"name":"Croft"},{"name":"Earl Shilton"},{"name":"Enderby"},{"name":"Fleckney"},{"name":"Glenfield"},{"name":"Great Glen"},{"name":"Houghton on the Hill"},{"name":"Kibworth Harcourt"},{"name":"Kirby Muxloe"},{"name":"Leicester"},{"name":"Leicestershire"},{"name":"Narborough"},{"name":"Oadby"},{"name":"Sapcote"},{"name":"Stoney Stanton"},{"name":"Syston"},{"name":"Wigston Magna"}]
