[{"name":"Alconbury"},{"name":"Barnack"},{"name":"Baston"},{"name":"Castor"},{"name":"Cowbit"},{"name":"Crowland"},{"name":"Emneth"},{"name":"Eye"},{"name":"Gedney Hill"},{"name":"Glinton"},{"name":"Helpston"},{"name":"Holbeach"},{"name":"Langtoft"},{"name":"March"},{"name":"Market Deeping"},{"name":"Moulton Chapel"},{"name":"Northborough"},{"name":"Oundle"},{"name":"Peterborough"},{"name":"Pinchbeck"},{"name":"Ramsey"},{"name":"Sawtry"},{"name":"Spalding"},{"name":"Stilton"},{"name":"Sutton Bridge"},{"name":"Terrington Saint John"},{"name":"Terrington St Clement"},{"name":"Thorney"},{"name":"Thurlby"},{"name":"Wansford"},{"name":"West Walton"},{"name":"Whaplode"},{"name":"Whittlesey"},{"name":"Wisbech"},{"name":"Wittering"},{"name":"Yaxley"}]
