[{"name":"Alderbury"},{"name":"Alderholt"},{"name":"Bishopstoke"},{"name":"Botley"},{"name":"Bransgore"},{"name":"Brockenhurst"},{"name":"Burley"},{"name":"Bursledon"},{"name":"Cadnam"},{"name":"Downton"},{"name":"East Dean"},{"name":"Eastleigh"},{"name":"Fordingbridge"},{"name":"Hamble-le-Rice"},{"name":"Hedge End"},{"name":"Hythe"},{"name":"Lyndhurst"},{"name":"Marchwood"},{"name":"Middle Winterslow"},{"name":"Netley"},{"name":"New Milton"},{"name":"North Baddesley"},{"name":"Ringwood"},{"name":"Romsey"},{"name":"Southampton"},{"name":"Sway"},{"name":"Totton"},{"name":"West End"},{"name":"West Wellow"},{"name":"Whiteparish"}]
