[{"name":"Agazzano"},{"name":"Albareto"},{"name":"Alberi"},{"name":"Albinea"},{"name":"Alseno"},{"name":"Altedo"},{"name":"Anzola dell'Emilia"},{"name":"Arceto"},{"name":"Argelato"},{"name":"Argenta"},{"name":"Argine"},{"name":"Baganzola"},{"name":"Baggiovara"},{"name":"Bagnarola"},{"name":"Bagno"},{"name":"Bagnolo in Piano"},{"name":"Baiso"},{"name":"Barbiano"},{"name":"Barco"},{"name":"Bardi"},{"name":"Baricella"},{"name":"Basilicagoiano"},{"name":"Basilicanova"},{"name":"Bastiglia"},{"name":"Bazzano"},{"name":"Bedonia"},{"name":"Bellaria-Igea Marina"},{"name":"Bentivoglio"},{"name":"Berceto"},{"name":"Berra"},{"name":"Bertinoro"},{"name":"Berzantina"},{"name":"Besenzone"},{"name":"Bettola"},{"name":"Bibbiano"},{"name":"Bobbio"},{"name":"Bologna"},{"name":"Bomporto"},{"name":"Bondeno"},{"name":"Bora Bassa"},{"name":"Bore"},{"name":"Borello"},{"name":"Boretto"},{"name":"Borghi"},{"name":"Borgo Tossignano"},{"name":"Borgo Val di Taro"},{"name":"Borgonovo Valtidone"},{"name":"Borgonuovo"},{"name":"Borzano"},{"name":"Bosco Mesola"},{"name":"Brescello"},{"name":"Bubano"},{"name":"Budrio"},{"name":"Busana"},{"name":"Busseto"},{"name":"Cà Dè Fabbri"},{"name":"Ca' di Sola"},{"name":"Cadè-Gaida"},{"name":"Cadelbosco di Sopra"},{"name":"Cadelbosco di Sotto"},{"name":"Calcara"},{"name":"Calderara di Reno"},{"name":"Calderino"},{"name":"Calendasco"},{"name":"Calerno"},{"name":"Calestano"},{"name":"Caminata"},{"name":"Campagnola Emilia"},{"name":"Campegine"},{"name":"Campogalliano"},{"name":"Camposanto"},{"name":"Camugnano"},{"name":"Caorso"},{"name":"Caprara"},{"name":"Carpaneto Piacentino"},{"name":"Carpi Centro"},{"name":"Carpineti"},{"name":"Casale"},{"name":"Casalecchio di Reno"},{"name":"Casalfiumanese"},{"name":"Casalgrande"},{"name":"Casina"},{"name":"Castel d'Aiano"},{"name":"Castel del Rio"},{"name":"Castel di Casio"},{"name":"Castel Guelfo di Bologna"},{"name":"Castel Maggiore"},{"name":"Castel San Giovanni"},{"name":"Castel San Pietro Terme"},{"name":"Casteldelci"},{"name":"Castelfranco Emilia"},{"name":"Castell'Arquato"},{"name":"Castellarano"},{"name":"Castelletto"},{"name":"Castello d'Argile"},{"name":"Castelnovo di Sotto"},{"name":"Castelnovo ne'Monti"},{"name":"Castelnuovo Rangone"},{"name":"Castelvetro di Modena"},{"name":"Castelvetro Piacentino"},{"name":"Castenaso"},{"name":"Castiglione dei Pepoli"},{"name":"Castrocaro Terme e Terra del Sole"},{"name":"Cattolica"},{"name":"Cavazzona"},{"name":"Cavezzo"},{"name":"Cavriago"},{"name":"Cento"},{"name":"Cerasolo"},{"name":"Cerignale"},{"name":"Cesena"},{"name":"Cesenatico"},{"name":"Ciano d'Enza"},{"name":"Civitella di Romagna"},{"name":"Classe"},{"name":"Coccanile-Cesta"},{"name":"Codemondo-Quaresimo"},{"name":"Codigoro"},{"name":"Codisotto"},{"name":"Coli"},{"name":"Collagna"},{"name":"Collecchio"},{"name":"Colombaro"},{"name":"Colorno"},{"name":"Comacchio"},{"name":"Compiano"},{"name":"Cona"},{"name":"Concordia sulla Secchia"},{"name":"Consandolo"},{"name":"Copparo"},{"name":"Corcagnano"},{"name":"Coriano"},{"name":"Corniglio"},{"name":"Corpo Reno"},{"name":"Corpolò"},{"name":"Correggio"},{"name":"Cortemaggiore"},{"name":"Crespellano"},{"name":"Crevalcore"},{"name":"Cusercoli"},{"name":"Decima"},{"name":"Dodici Morelli"},{"name":"Dosso"},{"name":"Dovadola"},{"name":"Dozza"},{"name":"Fabbrico"},{"name":"Fanano"},{"name":"Farini"},{"name":"Felegara"},{"name":"Felina"},{"name":"Felino"},{"name":"Fellegara"},{"name":"Ferrara"},{"name":"Ferriere"},{"name":"Fidenza"},{"name":"Finale Emilia"},{"name":"Fiorano"},{"name":"Fiorenzuola d'Arda"},{"name":"Fiumalbo-Dogana"},{"name":"Fiumana"},{"name":"Fogliano"},{"name":"Fognano"},{"name":"Fontanelice"},{"name":"Fontanellato"},{"name":"Fontevivo"},{"name":"Forche"},{"name":"Forlì"},{"name":"Forlimpopoli"},{"name":"Formica"},{"name":"Formigine"},{"name":"Formignana"},{"name":"Fornace Zarattini"},{"name":"Fornovo di Taro"},{"name":"Fossa"},{"name":"Fosso Ghiaia"},{"name":"Fossoli"},{"name":"Francolino"},{"name":"Frassinoro"},{"name":"Fratta Terme"},{"name":"Gaggio"},{"name":"Gaggio Montano"},{"name":"Gaiano"},{"name":"Gaibanella-Sant'Edigio"},{"name":"Galeata"},{"name":"Gallo"},{"name":"Gambettola"},{"name":"Gatteo a Mare"},{"name":"Gatteo-Sant'Angelo"},{"name":"Gazzola"},{"name":"Gemmano"},{"name":"Glorie"},{"name":"Godo"},{"name":"Goro"},{"name":"Gorzano"},{"name":"Gossolengo"},{"name":"Gragnano Trebbiense"},{"name":"Granarolo"},{"name":"Granarolo dell'Emilia e Viadagola"},{"name":"Grizzana"},{"name":"Grizzana Morandi"},{"name":"Gropparello"},{"name":"Gualtieri"},{"name":"Guastalla"},{"name":"Guiglia"},{"name":"Imola"},{"name":"Jolanda di Savoia"},{"name":"La Saletta-Tamara"},{"name":"Lagosanto"},{"name":"Lama"},{"name":"Langhirano"},{"name":"Lavezzola"},{"name":"Lentigione-Sorbolo a Mane"},{"name":"Lesignano de'Bagni"},{"name":"Lido Adriano"},{"name":"Lido degli Estensi"},{"name":"Lido di Pomposa-Lido degli Scacchi"},{"name":"Ligonchio"},{"name":"Limidi"},{"name":"Lizzano in Belvedere"},{"name":"Loiano"},{"name":"Longara"},{"name":"Longastrino"},{"name":"Longiano"},{"name":"Lugagnano Val d'Arda"},{"name":"Luzzara"},{"name":"Madonna Dell'Albero"},{"name":"Magreta"},{"name":"Malalbergo"},{"name":"Manzolino"},{"name":"Maranello"},{"name":"Marano sul Panaro"},{"name":"Marina di Ravenna"},{"name":"Marina Romea"},{"name":"Marsaglia"},{"name":"Marzabotto"},{"name":"Masi-Torello"},{"name":"Massa Finalese"},{"name":"Massa Fiscaglia"},{"name":"Massenzatico"},{"name":"Medesano"},{"name":"Medicina-Buda"},{"name":"Medolla"},{"name":"Meldola"},{"name":"Mercato Saraceno"},{"name":"Mesola"},{"name":"Mezzano"},{"name":"Mezzano Inferiore"},{"name":"Mezzogoro"},{"name":"Mezzolara"},{"name":"Migliarina"},{"name":"Migliarino"},{"name":"Migliaro"},{"name":"Milano Marittima"},{"name":"Minerbio"},{"name":"Mirabello"},{"name":"Mirandola"},{"name":"Misano Adriatico"},{"name":"Modena"},{"name":"Modigliana"},{"name":"Molinella"},{"name":"Molino del Pallone"},{"name":"Monchio delle Corti"},{"name":"Mondaino"},{"name":"Monghidoro"},{"name":"Montalbano"},{"name":"Montale"},{"name":"Monte Colombo"},{"name":"Monte San Giovanni"},{"name":"Montecavolo"},{"name":"Montecchio Emilia"},{"name":"Montechiarugolo"},{"name":"Montecreto"},{"name":"Montefiore Conca"},{"name":"Montefiorino"},{"name":"Montegridolfo"},{"name":"Monterenzio"},{"name":"Montescudo"},{"name":"Montese"},{"name":"Montiano"},{"name":"Monticelli d'Ongina"},{"name":"Monticelli Terme"},{"name":"Monzuno"},{"name":"Morciano di Romagna"},{"name":"Mordano"},{"name":"Morfasso"},{"name":"Mulino"},{"name":"Neviano degli Arduini"},{"name":"Nibbiano"},{"name":"Niviano"},{"name":"Noceto"},{"name":"Nonantola"},{"name":"Novafeltria"},{"name":"Novellara"},{"name":"Novi di Modena"},{"name":"Ospedaletto"},{"name":"Ostellato"},{"name":"Osteria Grande"},{"name":"Osteria Nuova"},{"name":"Ottone"},{"name":"Ozzano dell'Emilia"},{"name":"Ozzano Taro"},{"name":"Padulle"},{"name":"Palagano"},{"name":"Palanzano"},{"name":"Panighina"},{"name":"Parma"},{"name":"Pavullo nel Frignano"},{"name":"Pecorara"},{"name":"Pellegrino Parmense"},{"name":"Pennabilli"},{"name":"Piacenza"},{"name":"Pianello Val Tidone"},{"name":"Piangipane"},{"name":"Pianoro"},{"name":"Pietracuta"},{"name":"Pieve di Cento"},{"name":"Pievepelago"},{"name":"Pilastro"},{"name":"Pinarella"},{"name":"Piozzano"},{"name":"Pisignano"},{"name":"Piumazzo"},{"name":"Pizzano"},{"name":"Podenzano"},{"name":"Poggio Berni"},{"name":"Poggio Renatico"},{"name":"Polesine Parmense"},{"name":"Polinago"},{"name":"Ponte dell'Olio"},{"name":"Ponte della Venturina"},{"name":"Ponte Ronca"},{"name":"Ponte Taro"},{"name":"Pontegradella"},{"name":"Pontelangorino"},{"name":"Pontenure"},{"name":"Ponticella"},{"name":"Porotto-Cassama"},{"name":"Porporano"},{"name":"Porretta Terme"},{"name":"Portico di Romagna"},{"name":"Portico e San Benedetto"},{"name":"Porto Corsini"},{"name":"Porto Fuori"},{"name":"Porto Garibaldi"},{"name":"Portomaggiore"},{"name":"Poviglio"},{"name":"Pozza"},{"name":"Praticello"},{"name":"Pratissolo"},{"name":"Prato"},{"name":"Predappio"},{"name":"Premilcuore"},{"name":"Prignano"},{"name":"Prignano sulla Secchia"},{"name":"Progresso"},{"name":"Provincia di Ferrara"},{"name":"Provincia di Forlì-Cesena"},{"name":"Provincia di Modena"},{"name":"Provincia di Parma"},{"name":"Provincia di Piacenza"},{"name":"Provincia di Ravenna"},{"name":"Provincia di Reggio Emilia"},{"name":"Provincia di Rimini"},{"name":"Puianello"},{"name":"Pulce"},{"name":"Punta Marina"},{"name":"Quarantoli"},{"name":"Quartesana"},{"name":"Quarto Inferiore"},{"name":"Quattro Castella"},{"name":"Ramiola"},{"name":"Ramiseto"},{"name":"Rastignano-Carteria di Sesto"},{"name":"Ravarino"},{"name":"Reggio nell'Emilia"},{"name":"Reggiolo"},{"name":"Renazzo"},{"name":"Riale"},{"name":"Riccione"},{"name":"Riccò"},{"name":"Rimini"},{"name":"Rio Saliceto"},{"name":"Riolunato"},{"name":"Rivazzurra"},{"name":"Rivergaro"},{"name":"Ro"},{"name":"Rocca San Casciano"},{"name":"Roccabianca"},{"name":"Rolo"},{"name":"Roncocesi"},{"name":"Roncofreddo"},{"name":"Roncofreddo-Santa Paola"},{"name":"Roteglia"},{"name":"Rottofreno"},{"name":"Roveleto"},{"name":"Rovereto"},{"name":"Rubiera"},{"name":"Sala"},{"name":"Sala Baganza"},{"name":"Sala Bolognese"},{"name":"Salsomaggiore Terme"},{"name":"Saludecio"},{"name":"Salvaterra"},{"name":"Sam Marino"},{"name":"San Bartolomeo"},{"name":"San Bartolomeo In Bosco"},{"name":"San Benedetto Val di Sambro"},{"name":"San Biagio"},{"name":"San Carlo"},{"name":"San Cesario sul Panaro"},{"name":"San Clemente"},{"name":"San Damaso"},{"name":"San Felice sul Panaro"},{"name":"San Gabriele-Mondonuovo"},{"name":"San Giorgio di Piano"},{"name":"San Giorgio Piacentino"},{"name":"San Giovanni in Marignano"},{"name":"San Giovanni in Persiceto"},{"name":"San Giovanni-San Bernardino"},{"name":"San Giuseppe"},{"name":"San Lazzaro"},{"name":"San Leo"},{"name":"San Martino"},{"name":"San Martino dei Mulini"},{"name":"San Martino in Argine"},{"name":"San Martino in Rio"},{"name":"San Mauro a Mare"},{"name":"San Mauro Pascoli"},{"name":"San Michele dei Mucchietti"},{"name":"San Michele Tiorre"},{"name":"San Nicolò"},{"name":"San Pancrazio"},{"name":"San Piero in Bagno"},{"name":"San Pietro Capofiume"},{"name":"San Pietro in Casale"},{"name":"San Pietro in Cerro"},{"name":"San Pietro In Vincoli"},{"name":"San Polo"},{"name":"San Polo d'Enza"},{"name":"San Possidonio"},{"name":"San Prospero"},{"name":"San Secondo Parmense"},{"name":"San Venanzio"},{"name":"San Vincenzo"},{"name":"San Vito"},{"name":"Sant'Agata Bolognese"},{"name":"Sant'Agata Feltria"},{"name":"Sant'Agostino"},{"name":"Sant'Alberto"},{"name":"Sant'Andrea"},{"name":"Sant'Andrea in Casale"},{"name":"Sant'Antonio"},{"name":"Sant'Ilario d'Enza"},{"name":"Santa Croce Scuole"},{"name":"Santa Giustina"},{"name":"Santa Maria Codifiume"},{"name":"Santa Maria Nuova"},{"name":"Santa Monica-Cella"},{"name":"Santa Sofia"},{"name":"Santa Vittoria"},{"name":"Santarcangelo"},{"name":"Santerno"},{"name":"Santo Stefano-Carraie"},{"name":"Sarmato"},{"name":"Sarsina"},{"name":"Sasso Marconi"},{"name":"Sassuolo"},{"name":"Savarna-Conventello"},{"name":"Savignano sul Panaro"},{"name":"Savignano sul Rubicone"},{"name":"Savigno"},{"name":"Savio"},{"name":"Scandiano"},{"name":"Scortichino"},{"name":"Secchiano"},{"name":"Serra di Maiolo"},{"name":"Serramazzoni"},{"name":"Serravalle"},{"name":"Sesto Imolese"},{"name":"Sestola"},{"name":"Sissa"},{"name":"Sogliano al Rubicone"},{"name":"Solara"},{"name":"Soliera"},{"name":"Solignano"},{"name":"Solignano Nuovo"},{"name":"Soragna"},{"name":"Sorbara"},{"name":"Sorbolo"},{"name":"Spilamberto"},{"name":"Stazione Valmozzola"},{"name":"Talamello"},{"name":"Taneto"},{"name":"Terenzo"},{"name":"Tizzano Val Parma"},{"name":"Toano"},{"name":"Tornolo"},{"name":"Torriana"},{"name":"Torrile"},{"name":"Toscanella"},{"name":"Trarivi"},{"name":"Traversetolo"},{"name":"Travo"},{"name":"Trebbo"},{"name":"Trecasali"},{"name":"Tredozio"},{"name":"Tresigallo-Final di Rero"},{"name":"Vado"},{"name":"Varano De' Melegari"},{"name":"Varsi"},{"name":"Veggia-Villalunga"},{"name":"Venezzano"},{"name":"Ventoso"},{"name":"Vergato"},{"name":"Verghereto"},{"name":"Vernasca"},{"name":"Verucchio"},{"name":"Vetto"},{"name":"Vezzano sul Crostolo"},{"name":"Viano"},{"name":"Vicofertile"},{"name":"Vigarano Mainarda"},{"name":"Vigarano Pieve"},{"name":"Vigatto"},{"name":"Vignola"},{"name":"Vigolzone"},{"name":"Villa Fontana"},{"name":"Villa Minozzo"},{"name":"Villa Verucchio"},{"name":"Villanova"},{"name":"Villarotta"},{"name":"Voghiera"},{"name":"Voltana"},{"name":"Zerba"},{"name":"Ziano Piacentino"},{"name":"Zibello"},{"name":"Zocca"},{"name":"Zola Predosa"}]
