[{"name":"Anqing"},{"name":"Bagongshan"},{"name":"Baohe"},{"name":"Bengbu"},{"name":"Bengshan"},{"name":"Bowang"},{"name":"Bozhou"},{"name":"Changfeng"},{"name":"Chaohu"},{"name":"Chizhou"},{"name":"Chuzhou"},{"name":"Daguan"},{"name":"Dangshan"},{"name":"Dangtu"},{"name":"Datong"},{"name":"Dingyuan"},{"name":"Dongzhi"},{"name":"Duji"},{"name":"Fanchang"},{"name":"Feidong"},{"name":"Feixi"},{"name":"Fengtai"},{"name":"Fengyang"},{"name":"Funan"},{"name":"Fuyang"},{"name":"Guangde"},{"name":"Guichi"},{"name":"Guoyang"},{"name":"Guzhen"},{"name":"Hanshan"},{"name":"Hefei"},{"name":"Hexian"},{"name":"Huaibei"},{"name":"Huainan"},{"name":"Huaining"},{"name":"Huaishang"},{"name":"Huaiyuan"},{"name":"Huangshan"},{"name":"Huashan"},{"name":"Huizhou"},{"name":"Huoqiu"},{"name":"Huoshan"},{"name":"Jiaoqu"},{"name":"Jieshou"},{"name":"Jin'an"},{"name":"Jingde"},{"name":"Jinghu"},{"name":"Jingxian"},{"name":"Jinzhai"},{"name":"Jiujiang"},{"name":"Jixi"},{"name":"Lai'an"},{"name":"Langxi"},{"name":"Langya"},{"name":"Lieshan"},{"name":"Lingbi"},{"name":"Linquan"},{"name":"Lixin"},{"name":"Longzihu"},{"name":"Lu'an"},{"name":"Lu’an"},{"name":"Lujiang"},{"name":"Luyang"},{"name":"Ma'anshan"},{"name":"Mengcheng"},{"name":"Mingguang"},{"name":"Nanling"},{"name":"Nanqiao"},{"name":"Ningguo"},{"name":"Panji"},{"name":"Qianshan"},{"name":"Qiaocheng"},{"name":"Qimen"},{"name":"Qingyang"},{"name":"Quanjiao"},{"name":"Shexian"},{"name":"Shitai"},{"name":"Shouxian"},{"name":"Shucheng"},{"name":"Shushan"},{"name":"Sixian"},{"name":"Suixi"},{"name":"Susong"},{"name":"Suzhou"},{"name":"Taihe"},{"name":"Taihu"},{"name":"Tianchang"},{"name":"Tianjia'an"},{"name":"Tongcheng"},{"name":"Tongguan"},{"name":"Tongling"},{"name":"Tunxi"},{"name":"Wangjiang"},{"name":"Wanzhi"},{"name":"Wuhe"},{"name":"Wuhu"},{"name":"Wuwei"},{"name":"Xiangshan"},{"name":"Xiaoxian"},{"name":"Xiejiaji"},{"name":"Xiuning"},{"name":"Xuancheng"},{"name":"Xuanzhou"},{"name":"Yaohai"},{"name":"Yeji"},{"name":"Yi'an"},{"name":"Yijiang"},{"name":"Yingdong"},{"name":"Yingjiang"},{"name":"Yingquan"},{"name":"Yingshang"},{"name":"Yingzhou"},{"name":"Yixian"},{"name":"Yixiu"},{"name":"Yongqiao"},{"name":"Yu'an"},{"name":"Yuexi"},{"name":"Yuhui"},{"name":"Yushan"},{"name":"Zongyang"}]
